foil/__init__.py
foil/_version.py
foil/agent.py
foil/compose.py
foil/converters.py
foil/counting.py
foil/dates.py
foil/deserializers.py
foil/dotenv.py
foil/fileio.py
foil/filesys.py
foil/filters.py
foil/formatters.py
foil/ftp.py
foil/iteration.py
foil/logger.py
foil/order.py
foil/parsers.py
foil/paths.py
foil/patterns.py
foil/records.py
foil/serializers.py
foil/strings.py
foil/util.py
foil-0.2.7.dist-info/DESCRIPTION.rst
foil-0.2.7.dist-info/METADATA
foil-0.2.7.dist-info/RECORD
foil-0.2.7.dist-info/WHEEL
foil-0.2.7.dist-info/metadata.json
foil-0.2.7.dist-info/top_level.txt
