Metadata-Version: 2.0
Name: foil
Version: 0.2.7
Summary: Data cleaning and ETL utilities.
Home-page: https://github.com/portfoliome/foil
Author: Philip Martin
Author-email: philip.martin@censible.co
License: MIT
Keywords: ETL finance generators processing
Platform: UNKNOWN
Classifier: Development Status :: 5 - Production/Stable
Classifier: Intended Audience :: Developers
Classifier: Natural Language :: English
Classifier: Programming Language :: Python :: 3.5
Classifier: Programming Language :: Python :: 3.6
Classifier: Topic :: Utilities
Requires-Dist: iso8601
Requires-Dist: pytz
Requires-Dist: pyyaml
Requires-Dist: requests
Provides-Extra: develop
Requires-Dist: flake8; extra == 'develop'
Requires-Dist: pylint; extra == 'develop'
Provides-Extra: test
Requires-Dist: pytest; extra == 'test'
Requires-Dist: pytest-cov; extra == 'test'
